jenkins_job_transfers/__init__.py
jenkins_job_transfers/baseModule.py
jenkins_job_transfers/config.py
jenkins_job_transfers/utils.py
jenkins_job_transfers/version.py
jenkins_job_transfers/tests/__init__.py
jenkins_job_transfers/tests/config.py
jenkins_job_transfers/tests/conftest.py
jenkins_job_transfers/tests/test_check_and_install_plugin_dependencies.py
jenkins_job_transfers/tests/test_check_plugin_dependencies.py
jenkins_job_transfers/tests/test_check_publish_standards.py
jenkins_job_transfers/tests/test_connect.py
jenkins_job_transfers/tests/test_interim_cleanup.py
jenkins_job_transfers/tests/test_production_cleanup.py
jenkins_job_transfers/tests/test_servers.py
jenkins_job_transfers/tests/test_transfer.py
jenkins_job_transfers/tests/assets/xmlFilesForJobs/jobWithNoPluginsNoViews.xml
jenkins_job_transfers/tests/assets/xmlFilesForJobs/jobWithPluginsNoViews.xml
jenkins_job_transfers/tests/assets/xmlFilesForJobs/jobWithPluginsViews.xml
jenkins_job_transfers/tests/assets/xmlFilesForViews/viewWithJobsWithPlugins.xml
Context_Aware_Jenkins_Job_Transfers-1.1.1.dist-info/LICENSE
Context_Aware_Jenkins_Job_Transfers-1.1.1.dist-info/METADATA
Context_Aware_Jenkins_Job_Transfers-1.1.1.dist-info/WHEEL
Context_Aware_Jenkins_Job_Transfers-1.1.1.dist-info/top_level.txt
Context_Aware_Jenkins_Job_Transfers-1.1.1.dist-info/RECORD
