Metadata-Version: 2.2
Name: Context-Aware-Jenkins-Job-Transfers
Version: 1.1.1
Summary: Transfers Jobs b/w Jenkins Servers with relevant Views & Plugins. Transfers views with assosiated jobs and plugins in a Single Function Call.
Home-page: https://context-aware-jenkins-transfers-documentation.readthedocs.io/en/latest/
Author: Joel Thomas Chacko
Author-email: Joel Thomas Chacko <joeltc071@gmail.com>
Maintainer-email: Joel Thomas Chacko <joelkariyalil@gmail.com>
License:                                  Apache License
Project-URL: Repository, https://github.com/joelkariyalil/Jenkins-Transfers
Project-URL: Homepage, https://context-aware-jenkins-transfers-documentation.readthedocs.io/en/latest/index.html
Project-URL: Issues, https://github.com/joelkariyalil/Jenkins-Transfers/issues
Keywords: Jenkins,CICD,Jenkins-Transfer,Servers,TransferJobs,Plugins,TransferViews,Connect
Classifier: Programming Language :: Python :: 3
Classifier: License :: OSI Approved :: Apache Software License
Classifier: Operating System :: OS Independent
Requires-Python: >=3.6
License-File: LICENSE
Requires-Dist: python-jenkins==1.8.2
Requires-Dist: lxml==5.1.0
Requires-Dist: rich==13.7.1
Requires-Dist: pytest==8.3.4
